madminer/__init__.py
madminer/analysis/__init__.py
madminer/analysis/dataanalyzer.py
madminer/core/__init__.py
madminer/core/madminer.py
madminer/delphes/__init__.py
madminer/delphes/delphes_reader.py
madminer/fisherinformation/__init__.py
madminer/fisherinformation/geometry.py
madminer/fisherinformation/information.py
madminer/fisherinformation/manipulate.py
madminer/lhe/__init__.py
madminer/lhe/lhe_reader.py
madminer/likelihood/__init__.py
madminer/likelihood/base.py
madminer/likelihood/histo.py
madminer/likelihood/manipulate.py
madminer/likelihood/neural.py
madminer/limits/__init__.py
madminer/limits/asymptotic_limits.py
madminer/ml/__init__.py
madminer/ml/base.py
madminer/ml/double_parameterized_ratio.py
madminer/ml/ensemble.py
madminer/ml/likelihood.py
madminer/ml/lookup.py
madminer/ml/morphing_aware.py
madminer/ml/parameterized_ratio.py
madminer/ml/score.py
madminer/models/__init__.py
madminer/models/benchmarks.py
madminer/models/parameters.py
madminer/models/readers.py
madminer/models/systematics.py
madminer/plotting/__init__.py
madminer/plotting/distributions.py
madminer/plotting/fisherinformation.py
madminer/plotting/limits.py
madminer/plotting/morphing.py
madminer/plotting/uncertainties.py
madminer/sampling/__init__.py
madminer/sampling/combine.py
madminer/sampling/parameters.py
madminer/sampling/sampleaugmenter.py
madminer/utils/__init__.py
madminer/utils/histo.py
madminer/utils/morphing.py
madminer/utils/particle.py
madminer/utils/various.py
madminer/utils/interfaces/__init__.py
madminer/utils/interfaces/delphes.py
madminer/utils/interfaces/delphes_root.py
madminer/utils/interfaces/hdf5.py
madminer/utils/interfaces/hepmc.py
madminer/utils/interfaces/lhe.py
madminer/utils/interfaces/mg.py
madminer/utils/interfaces/mg_cards.py
madminer/utils/ml/__init__.py
madminer/utils/ml/eval.py
madminer/utils/ml/losses.py
madminer/utils/ml/trainer.py
madminer/utils/ml/utils.py
madminer/utils/ml/models/__init__.py
madminer/utils/ml/models/base.py
madminer-0.9.6.dist-info/LICENSE.md
madminer-0.9.6.dist-info/METADATA
madminer-0.9.6.dist-info/WHEEL
madminer-0.9.6.dist-info/top_level.txt
madminer-0.9.6.dist-info/RECORD
