Metadata-Version: 2.1
Name: madminer
Version: 0.9.6
Summary: Mining gold from MadGraph to improve limit setting in particle physics.
Home-page: https://github.com/madminer-tool/madminer
Author: Johann Brehmer, Felix Kling, Irina Espejo, Sinclert Perez, Kyle Cranmer
Author-email: johann.brehmer@nyu.edu
License: MIT
Project-URL: Documentation, https://madminer.readthedocs.io/en/latest/
Project-URL: Source Code, https://github.com/madminer-tool/madminer
Project-URL: Issue Tracker, https://github.com/madminer-tool/madminer/issues
Classifier: License :: OSI Approved :: MIT License
Classifier: Topic :: Scientific/Engineering
Classifier: Topic :: Scientific/Engineering :: Physics
Classifier: Programming Language :: Python
Classifier: Programming Language :: Python :: 3
Classifier: Programming Language :: Python :: 3.8
Classifier: Programming Language :: Python :: 3.9
Classifier: Programming Language :: Python :: 3.10
Requires-Python: >=3.8
License-File: LICENSE.md
Requires-Dist: h5py
Requires-Dist: matplotlib (>=2.0.0)
Requires-Dist: numpy (>=1.20.0)
Requires-Dist: particle (>=0.16.0)
Requires-Dist: scipy (>=1.0.0)
Requires-Dist: torch (>=1.0.0)
Requires-Dist: uproot3 (>=3.14.1)
Requires-Dist: vector (>=0.8.4)
Requires-Dist: sympy (>=0.7.4)
Provides-Extra: docs
Requires-Dist: myst-parser ; extra == 'docs'
Requires-Dist: numpydoc ; extra == 'docs'
Requires-Dist: sphinx (>=1.4) ; extra == 'docs'
Requires-Dist: sphinx-rtd-theme ; extra == 'docs'
Provides-Extra: examples
Requires-Dist: bqplot ; extra == 'examples'
Requires-Dist: pandas ; extra == 'examples'
Provides-Extra: lint
Requires-Dist: black[jupyter] (>=22.12.0) ; extra == 'lint'
Requires-Dist: isort (>=5.11.3) ; extra == 'lint'
Provides-Extra: test
Requires-Dist: pytest ; extra == 'test'
